radiology_swarm/__init__.py
radiology_swarm/data_converter.py
radiology_swarm/main.py
radiology_swarm/swarm_wrapper.py
radiology_swarm-0.0.3.dist-info/LICENSE
radiology_swarm-0.0.3.dist-info/METADATA
radiology_swarm-0.0.3.dist-info/WHEEL
radiology_swarm-0.0.3.dist-info/RECORD
